netboxkea/__about__.py
netboxkea/__init__.py
netboxkea/config.py
netboxkea/connector.py
netboxkea/entry_point.py
netboxkea/listener.py
netboxkea/logger.py
netboxkea/netbox.py
netboxkea/kea/__init__.py
netboxkea/kea/api.py
netboxkea/kea/app.py
netboxkea/kea/exceptions.py
examples/netbox-kea-dhcp.example.toml
examples/nginx-reverse-proxy
examples/systemd-netbox-kea-dhcp.service
netbox_kea_dhcp-0.0.1a10.dist-info/METADATA
netbox_kea_dhcp-0.0.1a10.dist-info/WHEEL
netbox_kea_dhcp-0.0.1a10.dist-info/entry_points.txt
netbox_kea_dhcp-0.0.1a10.dist-info/licenses/LICENSE
netbox_kea_dhcp-0.0.1a10.dist-info/RECORD
