Metadata-Version: 2.1
Name: netbox-kea-dhcp
Version: 0.0.1a10
Summary: Use netbox as subnets source for ISC Kea DHCP server
Project-URL: Homepage, https://github.com/francoismdj/netbox-kea-dhcp
Author: francoismdj
License-Expression: MIT
License-File: LICENSE
Classifier: Development Status :: 3 - Alpha
Classifier: Intended Audience :: Information Technology
Classifier: License :: OSI Approved :: MIT License
Classifier: Operating System :: OS Independent
Classifier: Programming Language :: Python :: 3
Classifier: Programming Language :: Python :: 3.8
Classifier: Programming Language :: Python :: 3.9
Classifier: Programming Language :: Python :: 3.10
Classifier: Topic :: System :: Systems Administration
Requires-Python: >=3.8
Requires-Dist: bottle~=0.12.25
Requires-Dist: pynetbox~=7.0.1
Requires-Dist: tomli>=1.1.0; python_version < '3.11'
